pyaphid/__init__.py
pyaphid/__main__.py
pyaphid/analyzer.py
pyaphid/cli.py
pyaphid/config.py
pyaphid/helpers.py
pyaphid/py.typed
pyaphid-0.3.1.dist-info/LICENSE
pyaphid-0.3.1.dist-info/METADATA
pyaphid-0.3.1.dist-info/WHEEL
pyaphid-0.3.1.dist-info/entry_points.txt
pyaphid-0.3.1.dist-info/RECORD
