Metadata-Version: 2.1
Name: pyaphid
Version: 0.3.1
Summary: Identify unwanted function calls in your code
Home-page: https://github.com/jvllmr/pyaphid
License: MIT
Author: Jan Vollmer
Author-email: jan@vllmr.dev
Requires-Python: >=3.8,<4.0
Classifier: Intended Audience :: Developers
Classifier: License :: OSI Approved :: MIT License
Classifier: Operating System :: OS Independent
Classifier: Programming Language :: Python :: 3
Classifier: Programming Language :: Python :: 3.8
Classifier: Programming Language :: Python :: 3.9
Classifier: Programming Language :: Python :: 3.10
Classifier: Programming Language :: Python :: 3.11
Classifier: Topic :: Software Development :: Bug Tracking
Classifier: Topic :: Software Development :: Quality Assurance
Classifier: Topic :: Utilities
Classifier: Typing :: Typed
Requires-Dist: ast-comments (>=1.0,<2.0)
Requires-Dist: tomli (>=2.0.1,<3.0.0)
Requires-Dist: typer[all] (<=1.0)
Project-URL: Repository, https://github.com/jvllmr/pyaphid
